ambrosio/__init__.py
ambrosio/ui/__init__.py
ambrosio/ui/cli/__init__.py
ambrosio/ui/cli/main.py
ambrosio-0.0.5.dist-info/LICENSE
ambrosio-0.0.5.dist-info/METADATA
ambrosio-0.0.5.dist-info/WHEEL
ambrosio-0.0.5.dist-info/entry_points.txt
ambrosio-0.0.5.dist-info/RECORD
